DiscriminantAnalysis/__init__.py
DiscriminantAnalysis/ida.py
DiscriminantAnalysis/qda.py
discanal/__init__.py
discanal/ida.py
discanal/qda.py
discanal-0.0.3.dist-info/METADATA
discanal-0.0.3.dist-info/WHEEL
discanal-0.0.3.dist-info/top_level.txt
discanal-0.0.3.dist-info/RECORD
