Metadata-Version: 2.1
Name: discanal
Version: 0.0.3
Summary: 판별분석
Home-page: https://github.com/KHR0907/datamining.git
Author: hyungrae0907
Author-email: hyungrae0907@gmail.com
Classifier: Programming Language :: Python :: 3
Classifier: License :: OSI Approved :: MIT License
Classifier: Operating System :: OS Independent
Requires-Python: >=3.6
Requires-Dist: scikit-learn
